{
  "swagger": "2.0",
  "info": {
    "description": "This is a dynamic API generated by PostgREST",
    "title": "PostgREST API",
    "version": "14.4"
  },
  "host": "mhfdzprxauqfczmtyizg.supabase.co:443",
  "basePath": "/",
  "schemes": [
    "https"
  ],
  "consumes": [
    "application/json",
    "application/vnd.pgrst.object+json;nulls=stripped",
    "application/vnd.pgrst.object+json",
    "text/csv"
  ],
  "produces": [
    "application/json",
    "application/vnd.pgrst.object+json;nulls=stripped",
    "application/vnd.pgrst.object+json",
    "text/csv"
  ],
  "paths": {
    "/": {
      "get": {
        "produces": [
          "application/openapi+json",
          "application/json"
        ],
        "responses": {
          "200": {
            "description": "OK"
          }
        },
        "summary": "OpenAPI description (this document)",
        "tags": [
          "Introspection"
        ]
      }
    },
    "/t_membership": {
      "get": {
        "parameters": [
          {
            "$ref": "#/parameters/rowFilter.t_membership.id"
          },
          {
            "$ref": "#/parameters/rowFilter.t_membership.nama"
          },
          {
            "$ref": "#/parameters/rowFilter.t_membership.telepon"
          },
          {
            "$ref": "#/parameters/rowFilter.t_membership.lokasi"
          },
          {
            "$ref": "#/parameters/select"
          },
          {
            "$ref": "#/parameters/order"
          },
          {
            "$ref": "#/parameters/range"
          },
          {
            "$ref": "#/parameters/rangeUnit"
          },
          {
            "$ref": "#/parameters/offset"
          },
          {
            "$ref": "#/parameters/limit"
          },
          {
            "$ref": "#/parameters/preferCount"
          }
        ],
        "responses": {
          "200": {
            "description": "OK",
            "schema": {
              "items": {
                "$ref": "#/definitions/t_membership"
              },
              "type": "array"
            }
          },
          "206": {
            "description": "Partial Content"
          }
        },
        "tags": [
          "t_membership"
        ]
      },
      "post": {
        "parameters": [
          {
            "$ref": "#/parameters/body.t_membership"
          },
          {
            "$ref": "#/parameters/select"
          },
          {
            "$ref": "#/parameters/preferPost"
          }
        ],
        "responses": {
          "201": {
            "description": "Created"
          }
        },
        "tags": [
          "t_membership"
        ]
      },
      "delete": {
        "parameters": [
          {
            "$ref": "#/parameters/rowFilter.t_membership.id"
          },
          {
            "$ref": "#/parameters/rowFilter.t_membership.nama"
          },
          {
            "$ref": "#/parameters/rowFilter.t_membership.telepon"
          },
          {
            "$ref": "#/parameters/rowFilter.t_membership.lokasi"
          },
          {
            "$ref": "#/parameters/preferReturn"
          }
        ],
        "responses": {
          "204": {
            "description": "No Content"
          }
        },
        "tags": [
          "t_membership"
        ]
      },
      "patch": {
        "parameters": [
          {
            "$ref": "#/parameters/rowFilter.t_membership.id"
          },
          {
            "$ref": "#/parameters/rowFilter.t_membership.nama"
          },
          {
            "$ref": "#/parameters/rowFilter.t_membership.telepon"
          },
          {
            "$ref": "#/parameters/rowFilter.t_membership.lokasi"
          },
          {
            "$ref": "#/parameters/body.t_membership"
          },
          {
            "$ref": "#/parameters/preferReturn"
          }
        ],
        "responses": {
          "204": {
            "description": "No Content"
          }
        },
        "tags": [
          "t_membership"
        ]
      }
    },
    "/t_live_performance": {
      "get": {
        "parameters": [
          {
            "$ref": "#/parameters/rowFilter.t_live_performance.id"
          },
          {
            "$ref": "#/parameters/rowFilter.t_live_performance.platform"
          },
          {
            "$ref": "#/parameters/rowFilter.t_live_performance.revenue"
          },
          {
            "$ref": "#/parameters/rowFilter.t_live_performance.live_number"
          },
          {
            "$ref": "#/parameters/rowFilter.t_live_performance.created_at"
          },
          {
            "$ref": "#/parameters/rowFilter.t_live_performance.updated_at"
          },
          {
            "$ref": "#/parameters/select"
          },
          {
            "$ref": "#/parameters/order"
          },
          {
            "$ref": "#/parameters/range"
          },
          {
            "$ref": "#/parameters/rangeUnit"
          },
          {
            "$ref": "#/parameters/offset"
          },
          {
            "$ref": "#/parameters/limit"
          },
          {
            "$ref": "#/parameters/preferCount"
          }
        ],
        "responses": {
          "200": {
            "description": "OK",
            "schema": {
              "items": {
                "$ref": "#/definitions/t_live_performance"
              },
              "type": "array"
            }
          },
          "206": {
            "description": "Partial Content"
          }
        },
        "tags": [
          "t_live_performance"
        ]
      },
      "post": {
        "parameters": [
          {
            "$ref": "#/parameters/body.t_live_performance"
          },
          {
            "$ref": "#/parameters/select"
          },
          {
            "$ref": "#/parameters/preferPost"
          }
        ],
        "responses": {
          "201": {
            "description": "Created"
          }
        },
        "tags": [
          "t_live_performance"
        ]
      },
      "delete": {
        "parameters": [
          {
            "$ref": "#/parameters/rowFilter.t_live_performance.id"
          },
          {
            "$ref": "#/parameters/rowFilter.t_live_performance.platform"
          },
          {
            "$ref": "#/parameters/rowFilter.t_live_performance.revenue"
          },
          {
            "$ref": "#/parameters/rowFilter.t_live_performance.live_number"
          },
          {
            "$ref": "#/parameters/rowFilter.t_live_performance.created_at"
          },
          {
            "$ref": "#/parameters/rowFilter.t_live_performance.updated_at"
          },
          {
            "$ref": "#/parameters/preferReturn"
          }
        ],
        "responses": {
          "204": {
            "description": "No Content"
          }
        },
        "tags": [
          "t_live_performance"
        ]
      },
      "patch": {
        "parameters": [
          {
            "$ref": "#/parameters/rowFilter.t_live_performance.id"
          },
          {
            "$ref": "#/parameters/rowFilter.t_live_performance.platform"
          },
          {
            "$ref": "#/parameters/rowFilter.t_live_performance.revenue"
          },
          {
            "$ref": "#/parameters/rowFilter.t_live_performance.live_number"
          },
          {
            "$ref": "#/parameters/rowFilter.t_live_performance.created_at"
          },
          {
            "$ref": "#/parameters/rowFilter.t_live_performance.updated_at"
          },
          {
            "$ref": "#/parameters/body.t_live_performance"
          },
          {
            "$ref": "#/parameters/preferReturn"
          }
        ],
        "responses": {
          "204": {
            "description": "No Content"
          }
        },
        "tags": [
          "t_live_performance"
        ]
      }
    },
    "/t_sales_order": {
      "get": {
        "parameters": [
          {
            "$ref": "#/parameters/rowFilter.t_sales_order.id"
          },
          {
            "$ref": "#/parameters/rowFilter.t_sales_order.created_at"
          },
          {
            "$ref": "#/parameters/rowFilter.t_sales_order.updated_at"
          },
          {
            "$ref": "#/parameters/rowFilter.t_sales_order.order_number"
          },
          {
            "$ref": "#/parameters/rowFilter.t_sales_order.terms_of_payment"
          },
          {
            "$ref": "#/parameters/rowFilter.t_sales_order.jumlah_piutang"
          },
          {
            "$ref": "#/parameters/rowFilter.t_sales_order.jumlah_cash"
          },
          {
            "$ref": "#/parameters/rowFilter.t_sales_order.diskon"
          },
          {
            "$ref": "#/parameters/rowFilter.t_sales_order.id_pelanggan"
          },
          {
            "$ref": "#/parameters/rowFilter.t_sales_order.total_item"
          },
          {
            "$ref": "#/parameters/rowFilter.t_sales_order.total_bayar"
          },
          {
            "$ref": "#/parameters/rowFilter.t_sales_order.coa_cash_id"
          },
          {
            "$ref": "#/parameters/rowFilter.t_sales_order.coa_credit_id"
          },
          {
            "$ref": "#/parameters/select"
          },
          {
            "$ref": "#/parameters/order"
          },
          {
            "$ref": "#/parameters/range"
          },
          {
            "$ref": "#/parameters/rangeUnit"
          },
          {
            "$ref": "#/parameters/offset"
          },
          {
            "$ref": "#/parameters/limit"
          },
          {
            "$ref": "#/parameters/preferCount"
          }
        ],
        "responses": {
          "200": {
            "description": "OK",
            "schema": {
              "items": {
                "$ref": "#/definitions/t_sales_order"
              },
              "type": "array"
            }
          },
          "206": {
            "description": "Partial Content"
          }
        },
        "tags": [
          "t_sales_order"
        ]
      },
      "post": {
        "parameters": [
          {
            "$ref": "#/parameters/body.t_sales_order"
          },
          {
            "$ref": "#/parameters/select"
          },
          {
            "$ref": "#/parameters/preferPost"
          }
        ],
        "responses": {
          "201": {
            "description": "Created"
          }
        },
        "tags": [
          "t_sales_order"
        ]
      },
      "delete": {
        "parameters": [
          {
            "$ref": "#/parameters/rowFilter.t_sales_order.id"
          },
          {
            "$ref": "#/parameters/rowFilter.t_sales_order.created_at"
          },
          {
            "$ref": "#/parameters/rowFilter.t_sales_order.updated_at"
          },
          {
            "$ref": "#/parameters/rowFilter.t_sales_order.order_number"
          },
          {
            "$ref": "#/parameters/rowFilter.t_sales_order.terms_of_payment"
          },
          {
            "$ref": "#/parameters/rowFilter.t_sales_order.jumlah_piutang"
          },
          {
            "$ref": "#/parameters/rowFilter.t_sales_order.jumlah_cash"
          },
          {
            "$ref": "#/parameters/rowFilter.t_sales_order.diskon"
          },
          {
            "$ref": "#/parameters/rowFilter.t_sales_order.id_pelanggan"
          },
          {
            "$ref": "#/parameters/rowFilter.t_sales_order.total_item"
          },
          {
            "$ref": "#/parameters/rowFilter.t_sales_order.total_bayar"
          },
          {
            "$ref": "#/parameters/rowFilter.t_sales_order.coa_cash_id"
          },
          {
            "$ref": "#/parameters/rowFilter.t_sales_order.coa_credit_id"
          },
          {
            "$ref": "#/parameters/preferReturn"
          }
        ],
        "responses": {
          "204": {
            "description": "No Content"
          }
        },
        "tags": [
          "t_sales_order"
        ]
      },
      "patch": {
        "parameters": [
          {
            "$ref": "#/parameters/rowFilter.t_sales_order.id"
          },
          {
            "$ref": "#/parameters/rowFilter.t_sales_order.created_at"
          },
          {
            "$ref": "#/parameters/rowFilter.t_sales_order.updated_at"
          },
          {
            "$ref": "#/parameters/rowFilter.t_sales_order.order_number"
          },
          {
            "$ref": "#/parameters/rowFilter.t_sales_order.terms_of_payment"
          },
          {
            "$ref": "#/parameters/rowFilter.t_sales_order.jumlah_piutang"
          },
          {
            "$ref": "#/parameters/rowFilter.t_sales_order.jumlah_cash"
          },
          {
            "$ref": "#/parameters/rowFilter.t_sales_order.diskon"
          },
          {
            "$ref": "#/parameters/rowFilter.t_sales_order.id_pelanggan"
          },
          {
            "$ref": "#/parameters/rowFilter.t_sales_order.total_item"
          },
          {
            "$ref": "#/parameters/rowFilter.t_sales_order.total_bayar"
          },
          {
            "$ref": "#/parameters/rowFilter.t_sales_order.coa_cash_id"
          },
          {
            "$ref": "#/parameters/rowFilter.t_sales_order.coa_credit_id"
          },
          {
            "$ref": "#/parameters/body.t_sales_order"
          },
          {
            "$ref": "#/parameters/preferReturn"
          }
        ],
        "responses": {
          "204": {
            "description": "No Content"
          }
        },
        "tags": [
          "t_sales_order"
        ]
      }
    },
    "/m_affiliator": {
      "get": {
        "parameters": [
          {
            "$ref": "#/parameters/rowFilter.m_affiliator.id"
          },
          {
            "$ref": "#/parameters/rowFilter.m_affiliator.nama"
          },
          {
            "$ref": "#/parameters/rowFilter.m_affiliator.platform"
          },
          {
            "$ref": "#/parameters/rowFilter.m_affiliator.created_at"
          },
          {
            "$ref": "#/parameters/rowFilter.m_affiliator.affiliator_number"
          },
          {
            "$ref": "#/parameters/select"
          },
          {
            "$ref": "#/parameters/order"
          },
          {
            "$ref": "#/parameters/range"
          },
          {
            "$ref": "#/parameters/rangeUnit"
          },
          {
            "$ref": "#/parameters/offset"
          },
          {
            "$ref": "#/parameters/limit"
          },
          {
            "$ref": "#/parameters/preferCount"
          }
        ],
        "responses": {
          "200": {
            "description": "OK",
            "schema": {
              "items": {
                "$ref": "#/definitions/m_affiliator"
              },
              "type": "array"
            }
          },
          "206": {
            "description": "Partial Content"
          }
        },
        "tags": [
          "m_affiliator"
        ]
      },
      "post": {
        "parameters": [
          {
            "$ref": "#/parameters/body.m_affiliator"
          },
          {
            "$ref": "#/parameters/select"
          },
          {
            "$ref": "#/parameters/preferPost"
          }
        ],
        "responses": {
          "201": {
            "description": "Created"
          }
        },
        "tags": [
          "m_affiliator"
        ]
      },
      "delete": {
        "parameters": [
          {
            "$ref": "#/parameters/rowFilter.m_affiliator.id"
          },
          {
            "$ref": "#/parameters/rowFilter.m_affiliator.nama"
          },
          {
            "$ref": "#/parameters/rowFilter.m_affiliator.platform"
          },
          {
            "$ref": "#/parameters/rowFilter.m_affiliator.created_at"
          },
          {
            "$ref": "#/parameters/rowFilter.m_affiliator.affiliator_number"
          },
          {
            "$ref": "#/parameters/preferReturn"
          }
        ],
        "responses": {
          "204": {
            "description": "No Content"
          }
        },
        "tags": [
          "m_affiliator"
        ]
      },
      "patch": {
        "parameters": [
          {
            "$ref": "#/parameters/rowFilter.m_affiliator.id"
          },
          {
            "$ref": "#/parameters/rowFilter.m_affiliator.nama"
          },
          {
            "$ref": "#/parameters/rowFilter.m_affiliator.platform"
          },
          {
            "$ref": "#/parameters/rowFilter.m_affiliator.created_at"
          },
          {
            "$ref": "#/parameters/rowFilter.m_affiliator.affiliator_number"
          },
          {
            "$ref": "#/parameters/body.m_affiliator"
          },
          {
            "$ref": "#/parameters/preferReturn"
          }
        ],
        "responses": {
          "204": {
            "description": "No Content"
          }
        },
        "tags": [
          "m_affiliator"
        ]
      }
    },
    "/t_content_statistic": {
      "get": {
        "parameters": [
          {
            "$ref": "#/parameters/rowFilter.t_content_statistic.id"
          },
          {
            "$ref": "#/parameters/rowFilter.t_content_statistic.content_planner_id"
          },
          {
            "$ref": "#/parameters/rowFilter.t_content_statistic.link"
          },
          {
            "$ref": "#/parameters/rowFilter.t_content_statistic.jumlah_view"
          },
          {
            "$ref": "#/parameters/rowFilter.t_content_statistic.monetasi"
          },
          {
            "$ref": "#/parameters/rowFilter.t_content_statistic.created_at"
          },
          {
            "$ref": "#/parameters/rowFilter.t_content_statistic.updated_at"
          },
          {
            "$ref": "#/parameters/select"
          },
          {
            "$ref": "#/parameters/order"
          },
          {
            "$ref": "#/parameters/range"
          },
          {
            "$ref": "#/parameters/rangeUnit"
          },
          {
            "$ref": "#/parameters/offset"
          },
          {
            "$ref": "#/parameters/limit"
          },
          {
            "$ref": "#/parameters/preferCount"
          }
        ],
        "responses": {
          "200": {
            "description": "OK",
            "schema": {
              "items": {
                "$ref": "#/definitions/t_content_statistic"
              },
              "type": "array"
            }
          },
          "206": {
            "description": "Partial Content"
          }
        },
        "tags": [
          "t_content_statistic"
        ]
      },
      "post": {
        "parameters": [
          {
            "$ref": "#/parameters/body.t_content_statistic"
          },
          {
            "$ref": "#/parameters/select"
          },
          {
            "$ref": "#/parameters/preferPost"
          }
        ],
        "responses": {
          "201": {
            "description": "Created"
          }
        },
        "tags": [
          "t_content_statistic"
        ]
      },
      "delete": {
        "parameters": [
          {
            "$ref": "#/parameters/rowFilter.t_content_statistic.id"
          },
          {
            "$ref": "#/parameters/rowFilter.t_content_statistic.content_planner_id"
          },
          {
            "$ref": "#/parameters/rowFilter.t_content_statistic.link"
          },
          {
            "$ref": "#/parameters/rowFilter.t_content_statistic.jumlah_view"
          },
          {
            "$ref": "#/parameters/rowFilter.t_content_statistic.monetasi"
          },
          {
            "$ref": "#/parameters/rowFilter.t_content_statistic.created_at"
          },
          {
            "$ref": "#/parameters/rowFilter.t_content_statistic.updated_at"
          },
          {
            "$ref": "#/parameters/preferReturn"
          }
        ],
        "responses": {
          "204": {
            "description": "No Content"
          }
        },
        "tags": [
          "t_content_statistic"
        ]
      },
      "patch": {
        "parameters": [
          {
            "$ref": "#/parameters/rowFilter.t_content_statistic.id"
          },
          {
            "$ref": "#/parameters/rowFilter.t_content_statistic.content_planner_id"
          },
          {
            "$ref": "#/parameters/rowFilter.t_content_statistic.link"
          },
          {
            "$ref": "#/parameters/rowFilter.t_content_statistic.jumlah_view"
          },
          {
            "$ref": "#/parameters/rowFilter.t_content_statistic.monetasi"
          },
          {
            "$ref": "#/parameters/rowFilter.t_content_statistic.created_at"
          },
          {
            "$ref": "#/parameters/rowFilter.t_content_statistic.updated_at"
          },
          {
            "$ref": "#/parameters/body.t_content_statistic"
          },
          {
            "$ref": "#/parameters/preferReturn"
          }
        ],
        "responses": {
          "204": {
            "description": "No Content"
          }
        },
        "tags": [
          "t_content_statistic"
        ]
      }
    },
    "/t_item": {
      "get": {
        "parameters": [
          {
            "$ref": "#/parameters/rowFilter.t_item.id_order"
          },
          {
            "$ref": "#/parameters/rowFilter.t_item.id_varian"
          },
          {
            "$ref": "#/parameters/rowFilter.t_item.harga"
          },
          {
            "$ref": "#/parameters/rowFilter.t_item.qty"
          },
          {
            "$ref": "#/parameters/rowFilter.t_item.harga_total"
          },
          {
            "$ref": "#/parameters/select"
          },
          {
            "$ref": "#/parameters/order"
          },
          {
            "$ref": "#/parameters/range"
          },
          {
            "$ref": "#/parameters/rangeUnit"
          },
          {
            "$ref": "#/parameters/offset"
          },
          {
            "$ref": "#/parameters/limit"
          },
          {
            "$ref": "#/parameters/preferCount"
          }
        ],
        "responses": {
          "200": {
            "description": "OK",
            "schema": {
              "items": {
                "$ref": "#/definitions/t_item"
              },
              "type": "array"
            }
          },
          "206": {
            "description": "Partial Content"
          }
        },
        "tags": [
          "t_item"
        ]
      },
      "post": {
        "parameters": [
          {
            "$ref": "#/parameters/body.t_item"
          },
          {
            "$ref": "#/parameters/select"
          },
          {
            "$ref": "#/parameters/preferPost"
          }
        ],
        "responses": {
          "201": {
            "description": "Created"
          }
        },
        "tags": [
          "t_item"
        ]
      },
      "delete": {
        "parameters": [
          {
            "$ref": "#/parameters/rowFilter.t_item.id_order"
          },
          {
            "$ref": "#/parameters/rowFilter.t_item.id_varian"
          },
          {
            "$ref": "#/parameters/rowFilter.t_item.harga"
          },
          {
            "$ref": "#/parameters/rowFilter.t_item.qty"
          },
          {
            "$ref": "#/parameters/rowFilter.t_item.harga_total"
          },
          {
            "$ref": "#/parameters/preferReturn"
          }
        ],
        "responses": {
          "204": {
            "description": "No Content"
          }
        },
        "tags": [
          "t_item"
        ]
      },
      "patch": {
        "parameters": [
          {
            "$ref": "#/parameters/rowFilter.t_item.id_order"
          },
          {
            "$ref": "#/parameters/rowFilter.t_item.id_varian"
          },
          {
            "$ref": "#/parameters/rowFilter.t_item.harga"
          },
          {
            "$ref": "#/parameters/rowFilter.t_item.qty"
          },
          {
            "$ref": "#/parameters/rowFilter.t_item.harga_total"
          },
          {
            "$ref": "#/parameters/body.t_item"
          },
          {
            "$ref": "#/parameters/preferReturn"
          }
        ],
        "responses": {
          "204": {
            "description": "No Content"
          }
        },
        "tags": [
          "t_item"
        ]
      }
    },
    "/t_content_planner": {
      "get": {
        "parameters": [
          {
            "$ref": "#/parameters/rowFilter.t_content_planner.id"
          },
          {
            "$ref": "#/parameters/rowFilter.t_content_planner.judul"
          },
          {
            "$ref": "#/parameters/rowFilter.t_content_planner.platform"
          },
          {
            "$ref": "#/parameters/rowFilter.t_content_planner.created_at"
          },
          {
            "$ref": "#/parameters/rowFilter.t_content_planner.affiliator_id"
          },
          {
            "$ref": "#/parameters/rowFilter.t_content_planner.jadwal"
          },
          {
            "$ref": "#/parameters/rowFilter.t_content_planner.tipe"
          },
          {
            "$ref": "#/parameters/rowFilter.t_content_planner.status"
          },
          {
            "$ref": "#/parameters/rowFilter.t_content_planner.content_number"
          },
          {
            "$ref": "#/parameters/select"
          },
          {
            "$ref": "#/parameters/order"
          },
          {
            "$ref": "#/parameters/range"
          },
          {
            "$ref": "#/parameters/rangeUnit"
          },
          {
            "$ref": "#/parameters/offset"
          },
          {
            "$ref": "#/parameters/limit"
          },
          {
            "$ref": "#/parameters/preferCount"
          }
        ],
        "responses": {
          "200": {
            "description": "OK",
            "schema": {
              "items": {
                "$ref": "#/definitions/t_content_planner"
              },
              "type": "array"
            }
          },
          "206": {
            "description": "Partial Content"
          }
        },
        "tags": [
          "t_content_planner"
        ]
      },
      "post": {
        "parameters": [
          {
            "$ref": "#/parameters/body.t_content_planner"
          },
          {
            "$ref": "#/parameters/select"
          },
          {
            "$ref": "#/parameters/preferPost"
          }
        ],
        "responses": {
          "201": {
            "description": "Created"
          }
        },
        "tags": [
          "t_content_planner"
        ]
      },
      "delete": {
        "parameters": [
          {
            "$ref": "#/parameters/rowFilter.t_content_planner.id"
          },
          {
            "$ref": "#/parameters/rowFilter.t_content_planner.judul"
          },
          {
            "$ref": "#/parameters/rowFilter.t_content_planner.platform"
          },
          {
            "$ref": "#/parameters/rowFilter.t_content_planner.created_at"
          },
          {
            "$ref": "#/parameters/rowFilter.t_content_planner.affiliator_id"
          },
          {
            "$ref": "#/parameters/rowFilter.t_content_planner.jadwal"
          },
          {
            "$ref": "#/parameters/rowFilter.t_content_planner.tipe"
          },
          {
            "$ref": "#/parameters/rowFilter.t_content_planner.status"
          },
          {
            "$ref": "#/parameters/rowFilter.t_content_planner.content_number"
          },
          {
            "$ref": "#/parameters/preferReturn"
          }
        ],
        "responses": {
          "204": {
            "description": "No Content"
          }
        },
        "tags": [
          "t_content_planner"
        ]
      },
      "patch": {
        "parameters": [
          {
            "$ref": "#/parameters/rowFilter.t_content_planner.id"
          },
          {
            "$ref": "#/parameters/rowFilter.t_content_planner.judul"
          },
          {
            "$ref": "#/parameters/rowFilter.t_content_planner.platform"
          },
          {
            "$ref": "#/parameters/rowFilter.t_content_planner.created_at"
          },
          {
            "$ref": "#/parameters/rowFilter.t_content_planner.affiliator_id"
          },
          {
            "$ref": "#/parameters/rowFilter.t_content_planner.jadwal"
          },
          {
            "$ref": "#/parameters/rowFilter.t_content_planner.tipe"
          },
          {
            "$ref": "#/parameters/rowFilter.t_content_planner.status"
          },
          {
            "$ref": "#/parameters/rowFilter.t_content_planner.content_number"
          },
          {
            "$ref": "#/parameters/body.t_content_planner"
          },
          {
            "$ref": "#/parameters/preferReturn"
          }
        ],
        "responses": {
          "204": {
            "description": "No Content"
          }
        },
        "tags": [
          "t_content_planner"
        ]
      }
    }
  },
  "definitions": {
    "t_membership": {
      "required": [
        "id",
        "nama"
      ],
      "properties": {
        "id": {
          "default": "gen_random_uuid()",
          "description": "Note:\nThis is a Primary Key.<pk/>",
          "format": "uuid",
          "type": "string"
        },
        "nama": {
          "format": "text",
          "type": "string"
        },
        "telepon": {
          "format": "character varying",
          "maxLength": 20,
          "type": "string"
        },
        "lokasi": {
          "format": "text",
          "type": "string"
        }
      },
      "type": "object"
    },
    "t_live_performance": {
      "required": [
        "id"
      ],
      "properties": {
        "id": {
          "default": "gen_random_uuid()",
          "description": "Note:\nThis is a Primary Key.<pk/>",
          "format": "uuid",
          "type": "string"
        },
        "platform": {
          "format": "text",
          "type": "string"
        },
        "revenue": {
          "default": 0,
          "format": "numeric",
          "type": "number"
        },
        "live_number": {
          "format": "text",
          "type": "string"
        },
        "created_at": {
          "default": "now()",
          "format": "timestamp with time zone",
          "type": "string"
        },
        "updated_at": {
          "default": "now()",
          "format": "timestamp with time zone",
          "type": "string"
        }
      },
      "type": "object"
    },
    "t_sales_order": {
      "required": [
        "id"
      ],
      "properties": {
        "id": {
          "default": "gen_random_uuid()",
          "description": "Note:\nThis is a Primary Key.<pk/>",
          "format": "uuid",
          "type": "string"
        },
        "created_at": {
          "default": "now()",
          "format": "timestamp with time zone",
          "type": "string"
        },
        "updated_at": {
          "default": "now()",
          "format": "timestamp with time zone",
          "type": "string"
        },
        "order_number": {
          "format": "text",
          "type": "string"
        },
        "terms_of_payment": {
          "default": 0,
          "format": "numeric",
          "type": "number"
        },
        "jumlah_piutang": {
          "default": 0,
          "format": "numeric",
          "type": "number"
        },
        "jumlah_cash": {
          "default": 0,
          "format": "numeric",
          "type": "number"
        },
        "diskon": {
          "default": 0,
          "format": "numeric",
          "type": "number"
        },
        "id_pelanggan": {
          "description": "Note:\nThis is a Foreign Key to `t_membership.id`.<fk table='t_membership' column='id'/>",
          "format": "uuid",
          "type": "string"
        },
        "total_item": {
          "default": 0,
          "format": "numeric",
          "type": "number"
        },
        "total_bayar": {
          "format": "numeric",
          "type": "number"
        },
        "coa_cash_id": {
          "format": "uuid",
          "type": "string"
        },
        "coa_credit_id": {
          "format": "uuid",
          "type": "string"
        }
      },
      "type": "object"
    },
    "m_affiliator": {
      "required": [
        "id"
      ],
      "properties": {
        "id": {
          "default": "gen_random_uuid()",
          "description": "Note:\nThis is a Primary Key.<pk/>",
          "format": "uuid",
          "type": "string"
        },
        "nama": {
          "format": "text",
          "type": "string"
        },
        "platform": {
          "format": "text",
          "type": "string"
        },
        "created_at": {
          "default": "now()",
          "format": "timestamp with time zone",
          "type": "string"
        },
        "affiliator_number": {
          "format": "text",
          "type": "string"
        }
      },
      "type": "object"
    },
    "t_content_statistic": {
      "required": [
        "id"
      ],
      "properties": {
        "id": {
          "default": "gen_random_uuid()",
          "description": "Note:\nThis is a Primary Key.<pk/>",
          "format": "uuid",
          "type": "string"
        },
        "content_planner_id": {
          "description": "Note:\nThis is a Foreign Key to `t_content_planner.id`.<fk table='t_content_planner' column='id'/>",
          "format": "uuid",
          "type": "string"
        },
        "link": {
          "format": "text",
          "type": "string"
        },
        "jumlah_view": {
          "default": 0,
          "format": "integer",
          "type": "integer"
        },
        "monetasi": {
          "default": 0,
          "format": "numeric",
          "type": "number"
        },
        "created_at": {
          "default": "now()",
          "format": "timestamp with time zone",
          "type": "string"
        },
        "updated_at": {
          "default": "now()",
          "format": "timestamp with time zone",
          "type": "string"
        }
      },
      "type": "object"
    },
    "t_item": {
      "required": [
        "id_order",
        "id_varian",
        "harga",
        "qty"
      ],
      "properties": {
        "id_order": {
          "description": "Note:\nThis is a Primary Key.<pk/>\nThis is a Foreign Key to `t_sales_order.id`.<fk table='t_sales_order' column='id'/>",
          "format": "uuid",
          "type": "string"
        },
        "id_varian": {
          "description": "Note:\nThis is a Primary Key.<pk/>",
          "format": "uuid",
          "type": "string"
        },
        "harga": {
          "default": 0,
          "format": "numeric",
          "type": "number"
        },
        "qty": {
          "default": 1,
          "format": "integer",
          "type": "integer"
        },
        "harga_total": {
          "format": "numeric",
          "type": "number"
        }
      },
      "type": "object"
    },
    "t_content_planner": {
      "required": [
        "id"
      ],
      "properties": {
        "id": {
          "default": "gen_random_uuid()",
          "description": "Note:\nThis is a Primary Key.<pk/>",
          "format": "uuid",
          "type": "string"
        },
        "judul": {
          "format": "text",
          "type": "string"
        },
        "platform": {
          "format": "text",
          "type": "string"
        },
        "created_at": {
          "default": "now()",
          "format": "timestamp with time zone",
          "type": "string"
        },
        "affiliator_id": {
          "description": "Note:\nThis is a Foreign Key to `m_affiliator.id`.<fk table='m_affiliator' column='id'/>",
          "format": "uuid",
          "type": "string"
        },
        "jadwal": {
          "format": "date",
          "type": "string"
        },
        "tipe": {
          "enum": [
            "story",
            "feed",
            "video",
            "live",
            "article",
            "other"
          ],
          "format": "sales.content_type",
          "type": "string"
        },
        "status": {
          "default": "direncanakan",
          "enum": [
            "terupload",
            "direncanakan",
            "dihapus"
          ],
          "format": "sales.content_status",
          "type": "string"
        },
        "content_number": {
          "format": "text",
          "type": "string"
        }
      },
      "type": "object"
    }
  },
  "parameters": {
    "preferParams": {
      "name": "Prefer",
      "description": "Preference",
      "required": false,
      "in": "header",
      "type": "string"
    },
    "preferReturn": {
      "name": "Prefer",
      "description": "Preference",
      "required": false,
      "enum": [
        "return=representation",
        "return=minimal",
        "return=none"
      ],
      "in": "header",
      "type": "string"
    },
    "preferCount": {
      "name": "Prefer",
      "description": "Preference",
      "required": false,
      "enum": [
        "count=none"
      ],
      "in": "header",
      "type": "string"
    },
    "preferPost": {
      "name": "Prefer",
      "description": "Preference",
      "required": false,
      "enum": [
        "return=representation",
        "return=minimal",
        "return=none",
        "resolution=ignore-duplicates",
        "resolution=merge-duplicates"
      ],
      "in": "header",
      "type": "string"
    },
    "select": {
      "name": "select",
      "description": "Filtering Columns",
      "required": false,
      "in": "query",
      "type": "string"
    },
    "on_conflict": {
      "name": "on_conflict",
      "description": "On Conflict",
      "required": false,
      "in": "query",
      "type": "string"
    },
    "order": {
      "name": "order",
      "description": "Ordering",
      "required": false,
      "in": "query",
      "type": "string"
    },
    "range": {
      "name": "Range",
      "description": "Limiting and Pagination",
      "required": false,
      "in": "header",
      "type": "string"
    },
    "rangeUnit": {
      "name": "Range-Unit",
      "description": "Limiting and Pagination",
      "required": false,
      "default": "items",
      "in": "header",
      "type": "string"
    },
    "offset": {
      "name": "offset",
      "description": "Limiting and Pagination",
      "required": false,
      "in": "query",
      "type": "string"
    },
    "limit": {
      "name": "limit",
      "description": "Limiting and Pagination",
      "required": false,
      "in": "query",
      "type": "string"
    },
    "body.t_membership": {
      "name": "t_membership",
      "description": "t_membership",
      "required": false,
      "in": "body",
      "schema": {
        "$ref": "#/definitions/t_membership"
      }
    },
    "rowFilter.t_membership.id": {
      "name": "id",
      "required": false,
      "in": "query",
      "type": "string"
    },
    "rowFilter.t_membership.nama": {
      "name": "nama",
      "required": false,
      "in": "query",
      "type": "string"
    },
    "rowFilter.t_membership.telepon": {
      "name": "telepon",
      "required": false,
      "in": "query",
      "type": "string"
    },
    "rowFilter.t_membership.lokasi": {
      "name": "lokasi",
      "required": false,
      "in": "query",
      "type": "string"
    },
    "body.t_live_performance": {
      "name": "t_live_performance",
      "description": "t_live_performance",
      "required": false,
      "in": "body",
      "schema": {
        "$ref": "#/definitions/t_live_performance"
      }
    },
    "rowFilter.t_live_performance.id": {
      "name": "id",
      "required": false,
      "in": "query",
      "type": "string"
    },
    "rowFilter.t_live_performance.platform": {
      "name": "platform",
      "required": false,
      "in": "query",
      "type": "string"
    },
    "rowFilter.t_live_performance.revenue": {
      "name": "revenue",
      "required": false,
      "in": "query",
      "type": "string"
    },
    "rowFilter.t_live_performance.live_number": {
      "name": "live_number",
      "required": false,
      "in": "query",
      "type": "string"
    },
    "rowFilter.t_live_performance.created_at": {
      "name": "created_at",
      "required": false,
      "in": "query",
      "type": "string"
    },
    "rowFilter.t_live_performance.updated_at": {
      "name": "updated_at",
      "required": false,
      "in": "query",
      "type": "string"
    },
    "body.t_sales_order": {
      "name": "t_sales_order",
      "description": "t_sales_order",
      "required": false,
      "in": "body",
      "schema": {
        "$ref": "#/definitions/t_sales_order"
      }
    },
    "rowFilter.t_sales_order.id": {
      "name": "id",
      "required": false,
      "in": "query",
      "type": "string"
    },
    "rowFilter.t_sales_order.created_at": {
      "name": "created_at",
      "required": false,
      "in": "query",
      "type": "string"
    },
    "rowFilter.t_sales_order.updated_at": {
      "name": "updated_at",
      "required": false,
      "in": "query",
      "type": "string"
    },
    "rowFilter.t_sales_order.order_number": {
      "name": "order_number",
      "required": false,
      "in": "query",
      "type": "string"
    },
    "rowFilter.t_sales_order.terms_of_payment": {
      "name": "terms_of_payment",
      "required": false,
      "in": "query",
      "type": "string"
    },
    "rowFilter.t_sales_order.jumlah_piutang": {
      "name": "jumlah_piutang",
      "required": false,
      "in": "query",
      "type": "string"
    },
    "rowFilter.t_sales_order.jumlah_cash": {
      "name": "jumlah_cash",
      "required": false,
      "in": "query",
      "type": "string"
    },
    "rowFilter.t_sales_order.diskon": {
      "name": "diskon",
      "required": false,
      "in": "query",
      "type": "string"
    },
    "rowFilter.t_sales_order.id_pelanggan": {
      "name": "id_pelanggan",
      "required": false,
      "in": "query",
      "type": "string"
    },
    "rowFilter.t_sales_order.total_item": {
      "name": "total_item",
      "required": false,
      "in": "query",
      "type": "string"
    },
    "rowFilter.t_sales_order.total_bayar": {
      "name": "total_bayar",
      "required": false,
      "in": "query",
      "type": "string"
    },
    "rowFilter.t_sales_order.coa_cash_id": {
      "name": "coa_cash_id",
      "required": false,
      "in": "query",
      "type": "string"
    },
    "rowFilter.t_sales_order.coa_credit_id": {
      "name": "coa_credit_id",
      "required": false,
      "in": "query",
      "type": "string"
    },
    "body.m_affiliator": {
      "name": "m_affiliator",
      "description": "m_affiliator",
      "required": false,
      "in": "body",
      "schema": {
        "$ref": "#/definitions/m_affiliator"
      }
    },
    "rowFilter.m_affiliator.id": {
      "name": "id",
      "required": false,
      "in": "query",
      "type": "string"
    },
    "rowFilter.m_affiliator.nama": {
      "name": "nama",
      "required": false,
      "in": "query",
      "type": "string"
    },
    "rowFilter.m_affiliator.platform": {
      "name": "platform",
      "required": false,
      "in": "query",
      "type": "string"
    },
    "rowFilter.m_affiliator.created_at": {
      "name": "created_at",
      "required": false,
      "in": "query",
      "type": "string"
    },
    "rowFilter.m_affiliator.affiliator_number": {
      "name": "affiliator_number",
      "required": false,
      "in": "query",
      "type": "string"
    },
    "body.t_content_statistic": {
      "name": "t_content_statistic",
      "description": "t_content_statistic",
      "required": false,
      "in": "body",
      "schema": {
        "$ref": "#/definitions/t_content_statistic"
      }
    },
    "rowFilter.t_content_statistic.id": {
      "name": "id",
      "required": false,
      "in": "query",
      "type": "string"
    },
    "rowFilter.t_content_statistic.content_planner_id": {
      "name": "content_planner_id",
      "required": false,
      "in": "query",
      "type": "string"
    },
    "rowFilter.t_content_statistic.link": {
      "name": "link",
      "required": false,
      "in": "query",
      "type": "string"
    },
    "rowFilter.t_content_statistic.jumlah_view": {
      "name": "jumlah_view",
      "required": false,
      "in": "query",
      "type": "string"
    },
    "rowFilter.t_content_statistic.monetasi": {
      "name": "monetasi",
      "required": false,
      "in": "query",
      "type": "string"
    },
    "rowFilter.t_content_statistic.created_at": {
      "name": "created_at",
      "required": false,
      "in": "query",
      "type": "string"
    },
    "rowFilter.t_content_statistic.updated_at": {
      "name": "updated_at",
      "required": false,
      "in": "query",
      "type": "string"
    },
    "body.t_item": {
      "name": "t_item",
      "description": "t_item",
      "required": false,
      "in": "body",
      "schema": {
        "$ref": "#/definitions/t_item"
      }
    },
    "rowFilter.t_item.id_order": {
      "name": "id_order",
      "required": false,
      "in": "query",
      "type": "string"
    },
    "rowFilter.t_item.id_varian": {
      "name": "id_varian",
      "required": false,
      "in": "query",
      "type": "string"
    },
    "rowFilter.t_item.harga": {
      "name": "harga",
      "required": false,
      "in": "query",
      "type": "string"
    },
    "rowFilter.t_item.qty": {
      "name": "qty",
      "required": false,
      "in": "query",
      "type": "string"
    },
    "rowFilter.t_item.harga_total": {
      "name": "harga_total",
      "required": false,
      "in": "query",
      "type": "string"
    },
    "body.t_content_planner": {
      "name": "t_content_planner",
      "description": "t_content_planner",
      "required": false,
      "in": "body",
      "schema": {
        "$ref": "#/definitions/t_content_planner"
      }
    },
    "rowFilter.t_content_planner.id": {
      "name": "id",
      "required": false,
      "in": "query",
      "type": "string"
    },
    "rowFilter.t_content_planner.judul": {
      "name": "judul",
      "required": false,
      "in": "query",
      "type": "string"
    },
    "rowFilter.t_content_planner.platform": {
      "name": "platform",
      "required": false,
      "in": "query",
      "type": "string"
    },
    "rowFilter.t_content_planner.created_at": {
      "name": "created_at",
      "required": false,
      "in": "query",
      "type": "string"
    },
    "rowFilter.t_content_planner.affiliator_id": {
      "name": "affiliator_id",
      "required": false,
      "in": "query",
      "type": "string"
    },
    "rowFilter.t_content_planner.jadwal": {
      "name": "jadwal",
      "required": false,
      "in": "query",
      "type": "string"
    },
    "rowFilter.t_content_planner.tipe": {
      "name": "tipe",
      "required": false,
      "in": "query",
      "type": "string"
    },
    "rowFilter.t_content_planner.status": {
      "name": "status",
      "required": false,
      "in": "query",
      "type": "string"
    },
    "rowFilter.t_content_planner.content_number": {
      "name": "content_number",
      "required": false,
      "in": "query",
      "type": "string"
    }
  },
  "externalDocs": {
    "description": "PostgREST Documentation",
    "url": "https://postgrest.org/en/v14/references/api.html"
  }
}